jwt_apns_client/__init__.py
jwt_apns_client/cli.py
jwt_apns_client/jwt_apns_client.py
jwt_apns_client/utils.py
jwt_apns_client-0.1.0.dist-info/DESCRIPTION.rst
jwt_apns_client-0.1.0.dist-info/METADATA
jwt_apns_client-0.1.0.dist-info/RECORD
jwt_apns_client-0.1.0.dist-info/WHEEL
jwt_apns_client-0.1.0.dist-info/entry_points.txt
jwt_apns_client-0.1.0.dist-info/metadata.json
jwt_apns_client-0.1.0.dist-info/top_level.txt
