Metadata-Version: 2.0
Name: jwt-apns-client
Version: 0.1.0
Summary: APNs client using JWT
Home-page: https://github.com/mobelux/jwt_apns_client
Author: Justin Michalicek
Author-email: justin@mobelux.com
License: MIT license
Keywords: jwt_apns_client
Platform: UNKNOWN
Classifier: Development Status :: 2 - Pre-Alpha
Classifier: Intended Audience :: Developers
Classifier: License :: OSI Approved :: MIT License
Classifier: Natural Language :: English
Classifier: Programming Language :: Python :: 2
Classifier: Programming Language :: Python :: 2.7
Classifier: Programming Language :: Python :: 3
Classifier: Programming Language :: Python :: 3.4
Classifier: Programming Language :: Python :: 3.5
Requires-Dist: Click (>=6.0)
Requires-Dist: PyJWT (>=1.4.2)
Requires-Dist: cryptography (>=1.5.3)
Requires-Dist: hyper (>=0.7.0)
